LICENSE
MANIFEST.in
README.md
setup.py
QuickQuant.egg-info/PKG-INFO
QuickQuant.egg-info/SOURCES.txt
QuickQuant.egg-info/dependency_links.txt
QuickQuant.egg-info/top_level.txt
quickquant/__init__.py
quickquant.egg-info/PKG-INFO
quickquant.egg-info/SOURCES.txt
quickquant.egg-info/dependency_links.txt
quickquant.egg-info/top_level.txt
quickquant/indicators/adx.c
quickquant/indicators/atr.c
quickquant/indicators/bollinger_bands.c
quickquant/indicators/ema.c
quickquant/indicators/ichimoku.c
quickquant/indicators/macd.c
quickquant/indicators/rsi.c
quickquant/indicators/sma.c
quickquant/indicators/stochastic.c
quickquant/indicators/volume_profile.c
quickquant/models/american_binomial.c
quickquant/models/american_finite_difference.c
quickquant/models/american_trinomial.c
quickquant/models/asian_options.c
quickquant/models/barrier_options.c
quickquant/models/black_cox.c
quickquant/models/black_litterman.c
quickquant/models/black_scholes.c
quickquant/models/cir_model.c
quickquant/models/creditmetrics.c
quickquant/models/heston_model.c
quickquant/models/hull_white.c
quickquant/models/kalman_filter.c
quickquant/models/lookback_options.c
quickquant/models/markowitz.c
quickquant/models/merton_model.c
quickquant/models/risk_parity.c
quickquant/models/swaptions.c
quickquant/models/vasicek_model.c
quickquant/data/__init__.py
quickquant/data/alpha_vantage.py
quickquant/data/clean_data.py
quickquant/data/fetch_data.py
quickquant/data/normalize.py
quickquant/data/yahoo_finance.py
quickquant/indicators/__init__.py
quickquant/indicators/adx.c
quickquant/indicators/adx.pyx
quickquant/indicators/atr.c
quickquant/indicators/atr.pyx
quickquant/indicators/bollinger_bands.c
quickquant/indicators/bollinger_bands.pyx
quickquant/indicators/ema.c
quickquant/indicators/ema.pyx
quickquant/indicators/ichimoku.c
quickquant/indicators/ichimoku.pyx
quickquant/indicators/macd.c
quickquant/indicators/macd.pyx
quickquant/indicators/rsi.c
quickquant/indicators/rsi.pyx
quickquant/indicators/sma.c
quickquant/indicators/sma.pyx
quickquant/indicators/stochastic.c
quickquant/indicators/stochastic.pyx
quickquant/indicators/volume_profile.c
quickquant/indicators/volume_profile.pyx
quickquant/indicators/vwma.pyx
quickquant/models/__init__.py
quickquant/models/american_binomial.c
