Metadata-Version: 2.1
Name: quickquant
Version: 0.2.0
Summary: A fast quant finance library
Author: Nabarup Ghosh
Author-email: nabarupeducation@gmail.com
License: Apache License 2.0
Classifier: Programming Language :: Python :: 3
Classifier: License :: OSI Approved :: Apache Software License
Classifier: Operating System :: OS Independent
License-File: LICENSE
